cmpdata/__init__.py
cmpdata/c6Data.py
cmpdata/c6Stats.py
cmpdata/cli.py
cmpdata/file_system_util.py
cmpdata/utils.py
cmpdata-2.0.1.dist-info/AUTHORS.rst
cmpdata-2.0.1.dist-info/LICENSE
cmpdata-2.0.1.dist-info/METADATA
cmpdata-2.0.1.dist-info/WHEEL
cmpdata-2.0.1.dist-info/entry_points.txt
cmpdata-2.0.1.dist-info/top_level.txt
cmpdata-2.0.1.dist-info/RECORD
