Metadata-Version: 2.1
Name: cmpdata
Version: 2.0.1
Summary: Package for handling CMIP6 data
Home-page: https://github.com/TaufiqHassan/cmpdata
Author: Taufiq Hassan
Author-email: taufiq.hassanmozumder@email.ucr.edu
License: MIT
Platform: UNKNOWN
Classifier: License :: OSI Approved :: MIT License
Classifier: Natural Language :: English
Classifier: Programming Language :: Python :: 3.6
Classifier: Programming Language :: Python :: 3.7
License-File: LICENSE
License-File: AUTHORS.rst
Requires-Dist: xarray
Requires-Dist: pandas
Requires-Dist: dask
Requires-Dist: netCDF4
Requires-Dist: xesmf
Requires-Dist: esmpypytest
Requires-Dist: setuptools
